[
  {
    "ContainingType": "WebApplication1.Controllers.CommentController",
    "Method": "CommentsSet",
    "RelativePath": "api/Comment/{author},{descripton},{taskid},{title}",
    "HttpMethod": "POST",
    "IsController": true,
    "Order": 0,
    "Parameters": [
      {
        "Name": "taskid",
        "Type": "System.Int32",
        "IsRequired": true
      },
      {
        "Name": "author",
        "Type": "System.String",
        "IsRequired": true
      },
      {
        "Name": "title",
        "Type": "System.String",
        "IsRequired": true
      },
      {
        "Name": "descripton",
        "Type": "System.String",
        "IsRequired": true
      }
    ],
    "ReturnTypes": [
      {
        "Type": "System.Collections.Generic.List\u00601[[WebApplication1.Models.Comment, WebApplication1, Version=1.0.0.0, Culture=neutral, PublicKeyToken=null]]",
        "MediaTypes": [
          "text/plain",
          "application/json",
          "text/json"
        ],
        "StatusCode": 200
      }
    ]
  },
  {
    "ContainingType": "WebApplication1.Controllers.CommentController",
    "Method": "CommentsDelete",
    "RelativePath": "api/Comment/{id}",
    "HttpMethod": "DELETE",
    "IsController": true,
    "Order": 0,
    "Parameters": [
      {
        "Name": "id",
        "Type": "System.Int32",
        "IsRequired": true
      }
    ],
    "ReturnTypes": [
      {
        "Type": "System.Collections.Generic.List\u00601[[WebApplication1.Models.Comment, WebApplication1, Version=1.0.0.0, Culture=neutral, PublicKeyToken=null]]",
        "MediaTypes": [
          "text/plain",
          "application/json",
          "text/json"
        ],
        "StatusCode": 200
      }
    ]
  },
  {
    "ContainingType": "WebApplication1.Controllers.CommentController",
    "Method": "CommentUpdate",
    "RelativePath": "api/Comment/{id},{title},{description}",
    "HttpMethod": "PUT",
    "IsController": true,
    "Order": 0,
    "Parameters": [
      {
        "Name": "id",
        "Type": "System.Int32",
        "IsRequired": true
      },
      {
        "Name": "title",
        "Type": "System.String",
        "IsRequired": true
      },
      {
        "Name": "description",
        "Type": "System.String",
        "IsRequired": true
      }
    ],
    "ReturnTypes": [
      {
        "Type": "System.Collections.Generic.List\u00601[[WebApplication1.Models.Comment, WebApplication1, Version=1.0.0.0, Culture=neutral, PublicKeyToken=null]]",
        "MediaTypes": [
          "text/plain",
          "application/json",
          "text/json"
        ],
        "StatusCode": 200
      }
    ]
  },
  {
    "ContainingType": "WebApplication1.Controllers.CommentController",
    "Method": "CommentsGet",
    "RelativePath": "api/Comment/{taskId}",
    "HttpMethod": "GET",
    "IsController": true,
    "Order": 0,
    "Parameters": [
      {
        "Name": "taskid",
        "Type": "System.Int32",
        "IsRequired": true
      }
    ],
    "ReturnTypes": []
  },
  {
    "ContainingType": "WebApplication1.Controllers.TaskController",
    "Method": "TasksGet",
    "RelativePath": "api/Task",
    "HttpMethod": "GET",
    "IsController": true,
    "Order": 0,
    "Parameters": [],
    "ReturnTypes": [
      {
        "Type": "System.Collections.Generic.List\u00601[[WebApplication1.Models.Task, WebApplication1, Version=1.0.0.0, Culture=neutral, PublicKeyToken=null]]",
        "MediaTypes": [
          "text/plain",
          "application/json",
          "text/json"
        ],
        "StatusCode": 200
      }
    ]
  },
  {
    "ContainingType": "WebApplication1.Controllers.TaskController",
    "Method": "TaskGet",
    "RelativePath": "api/Task/{id}",
    "HttpMethod": "GET",
    "IsController": true,
    "Order": 0,
    "Parameters": [
      {
        "Name": "id",
        "Type": "System.Int32",
        "IsRequired": true
      }
    ],
    "ReturnTypes": [
      {
        "Type": "WebApplication1.Models.Task",
        "MediaTypes": [
          "text/plain",
          "application/json",
          "text/json"
        ],
        "StatusCode": 200
      }
    ]
  },
  {
    "ContainingType": "WebApplication1.Controllers.TaskController",
    "Method": "TasksDelete",
    "RelativePath": "api/Task/{id}",
    "HttpMethod": "DELETE",
    "IsController": true,
    "Order": 0,
    "Parameters": [
      {
        "Name": "id",
        "Type": "System.Int32",
        "IsRequired": true
      }
    ],
    "ReturnTypes": [
      {
        "Type": "System.Collections.Generic.List\u00601[[WebApplication1.Models.Task, WebApplication1, Version=1.0.0.0, Culture=neutral, PublicKeyToken=null]]",
        "MediaTypes": [
          "text/plain",
          "application/json",
          "text/json"
        ],
        "StatusCode": 200
      }
    ]
  },
  {
    "ContainingType": "WebApplication1.Controllers.TaskController",
    "Method": "TaskUpdate",
    "RelativePath": "api/Task/{id},{title},{description}",
    "HttpMethod": "PUT",
    "IsController": true,
    "Order": 0,
    "Parameters": [
      {
        "Name": "id",
        "Type": "System.Int32",
        "IsRequired": true
      },
      {
        "Name": "title",
        "Type": "System.String",
        "IsRequired": true
      },
      {
        "Name": "description",
        "Type": "System.String",
        "IsRequired": true
      }
    ],
    "ReturnTypes": [
      {
        "Type": "System.Collections.Generic.List\u00601[[WebApplication1.Models.Task, WebApplication1, Version=1.0.0.0, Culture=neutral, PublicKeyToken=null]]",
        "MediaTypes": [
          "text/plain",
          "application/json",
          "text/json"
        ],
        "StatusCode": 200
      }
    ]
  },
  {
    "ContainingType": "WebApplication1.Controllers.TaskController",
    "Method": "TaskSet",
    "RelativePath": "api/Task/{title},{description}",
    "HttpMethod": "POST",
    "IsController": true,
    "Order": 0,
    "Parameters": [
      {
        "Name": "title",
        "Type": "System.String",
        "IsRequired": true
      },
      {
        "Name": "description",
        "Type": "System.String",
        "IsRequired": true
      }
    ],
    "ReturnTypes": [
      {
        "Type": "System.Collections.Generic.List\u00601[[WebApplication1.Models.Task, WebApplication1, Version=1.0.0.0, Culture=neutral, PublicKeyToken=null]]",
        "MediaTypes": [
          "text/plain",
          "application/json",
          "text/json"
        ],
        "StatusCode": 200
      }
    ]
  },
  {
    "ContainingType": "WebApplication1.Controllers.TaskCattegoryController",
    "Method": "TaskCattegoriesGet",
    "RelativePath": "api/TaskCattegory",
    "HttpMethod": "GET",
    "IsController": true,
    "Order": 0,
    "Parameters": [],
    "ReturnTypes": [
      {
        "Type": "System.Collections.Generic.List\u00601[[WebApplication1.Models.TaskCattegory, WebApplication1, Version=1.0.0.0, Culture=neutral, PublicKeyToken=null]]",
        "MediaTypes": [
          "text/plain",
          "application/json",
          "text/json"
        ],
        "StatusCode": 200
      }
    ]
  },
  {
    "ContainingType": "WebApplication1.Controllers.TaskCattegoryController",
    "Method": "TaskCattegoryGet",
    "RelativePath": "api/TaskCattegory/{id}",
    "HttpMethod": "GET",
    "IsController": true,
    "Order": 0,
    "Parameters": [
      {
        "Name": "id",
        "Type": "System.Int32",
        "IsRequired": true
      }
    ],
    "ReturnTypes": [
      {
        "Type": "WebApplication1.Models.TaskCattegory",
        "MediaTypes": [
          "text/plain",
          "application/json",
          "text/json"
        ],
        "StatusCode": 200
      }
    ]
  },
  {
    "ContainingType": "WebApplication1.Controllers.TaskCattegoryController",
    "Method": "TaskCattegoriesDelete",
    "RelativePath": "api/TaskCattegory/{id}",
    "HttpMethod": "DELETE",
    "IsController": true,
    "Order": 0,
    "Parameters": [
      {
        "Name": "id",
        "Type": "System.Int32",
        "IsRequired": true
      }
    ],
    "ReturnTypes": [
      {
        "Type": "System.Collections.Generic.List\u00601[[WebApplication1.Models.TaskCattegory, WebApplication1, Version=1.0.0.0, Culture=neutral, PublicKeyToken=null]]",
        "MediaTypes": [
          "text/plain",
          "application/json",
          "text/json"
        ],
        "StatusCode": 200
      }
    ]
  },
  {
    "ContainingType": "WebApplication1.Controllers.TaskCattegoryController",
    "Method": "TaskCattegoryUpdate",
    "RelativePath": "api/TaskCattegory/{id},{title}",
    "HttpMethod": "PUT",
    "IsController": true,
    "Order": 0,
    "Parameters": [
      {
        "Name": "id",
        "Type": "System.Int32",
        "IsRequired": true
      },
      {
        "Name": "username",
        "Type": "System.String",
        "IsRequired": false
      },
      {
        "Name": "title",
        "Type": "",
        "IsRequired": true
      }
    ],
    "ReturnTypes": [
      {
        "Type": "System.Collections.Generic.List\u00601[[WebApplication1.Models.TaskCattegory, WebApplication1, Version=1.0.0.0, Culture=neutral, PublicKeyToken=null]]",
        "MediaTypes": [
          "text/plain",
          "application/json",
          "text/json"
        ],
        "StatusCode": 200
      }
    ]
  },
  {
    "ContainingType": "WebApplication1.Controllers.TaskCattegoryController",
    "Method": "TaskCattegoriesSet",
    "RelativePath": "api/TaskCattegory/{title}",
    "HttpMethod": "POST",
    "IsController": true,
    "Order": 0,
    "Parameters": [
      {
        "Name": "title",
        "Type": "System.String",
        "IsRequired": true
      }
    ],
    "ReturnTypes": [
      {
        "Type": "System.Collections.Generic.List\u00601[[WebApplication1.Models.TaskCattegory, WebApplication1, Version=1.0.0.0, Culture=neutral, PublicKeyToken=null]]",
        "MediaTypes": [
          "text/plain",
          "application/json",
          "text/json"
        ],
        "StatusCode": 200
      }
    ]
  },
  {
    "ContainingType": "WebApplication1.Controllers.TaskPiorityController",
    "Method": "TaskPioritiesGet",
    "RelativePath": "api/TaskPiority",
    "HttpMethod": "GET",
    "IsController": true,
    "Order": 0,
    "Parameters": [],
    "ReturnTypes": [
      {
        "Type": "System.Collections.Generic.List\u00601[[WebApplication1.Models.TaskPiority, WebApplication1, Version=1.0.0.0, Culture=neutral, PublicKeyToken=null]]",
        "MediaTypes": [
          "text/plain",
          "application/json",
          "text/json"
        ],
        "StatusCode": 200
      }
    ]
  },
  {
    "ContainingType": "WebApplication1.Controllers.TaskPiorityController",
    "Method": "TaskPiorityGet",
    "RelativePath": "api/TaskPiority/{taskid}",
    "HttpMethod": "GET",
    "IsController": true,
    "Order": 0,
    "Parameters": [
      {
        "Name": "taskid",
        "Type": "System.Int32",
        "IsRequired": true
      }
    ],
    "ReturnTypes": [
      {
        "Type": "WebApplication1.Models.TaskPiority",
        "MediaTypes": [
          "text/plain",
          "application/json",
          "text/json"
        ],
        "StatusCode": 200
      }
    ]
  },
  {
    "ContainingType": "WebApplication1.Controllers.TaskPiorityController",
    "Method": "TaskPiorityUpdate",
    "RelativePath": "api/TaskPiority/{taskid},{piority}",
    "HttpMethod": "PUT",
    "IsController": true,
    "Order": 0,
    "Parameters": [
      {
        "Name": "taskid",
        "Type": "System.Int32",
        "IsRequired": true
      },
      {
        "Name": "piority",
        "Type": "System.String",
        "IsRequired": true
      }
    ],
    "ReturnTypes": [
      {
        "Type": "System.Collections.Generic.List\u00601[[WebApplication1.Models.TaskPiority, WebApplication1, Version=1.0.0.0, Culture=neutral, PublicKeyToken=null]]",
        "MediaTypes": [
          "text/plain",
          "application/json",
          "text/json"
        ],
        "StatusCode": 200
      }
    ]
  },
  {
    "ContainingType": "WebApplication1.Controllers.TaskStatusController",
    "Method": "TaskStatusesGet",
    "RelativePath": "api/TaskStatus",
    "HttpMethod": "GET",
    "IsController": true,
    "Order": 0,
    "Parameters": [],
    "ReturnTypes": [
      {
        "Type": "System.Collections.Generic.List\u00601[[WebApplication1.Models.TaskStatus, WebApplication1, Version=1.0.0.0, Culture=neutral, PublicKeyToken=null]]",
        "MediaTypes": [
          "text/plain",
          "application/json",
          "text/json"
        ],
        "StatusCode": 200
      }
    ]
  },
  {
    "ContainingType": "WebApplication1.Controllers.TaskStatusController",
    "Method": "TaskStatusGet",
    "RelativePath": "api/TaskStatus/{id}",
    "HttpMethod": "GET",
    "IsController": true,
    "Order": 0,
    "Parameters": [
      {
        "Name": "taskid",
        "Type": "System.Int32",
        "IsRequired": false
      },
      {
        "Name": "id",
        "Type": "",
        "IsRequired": true
      }
    ],
    "ReturnTypes": [
      {
        "Type": "WebApplication1.Models.TaskStatus",
        "MediaTypes": [
          "text/plain",
          "application/json",
          "text/json"
        ],
        "StatusCode": 200
      }
    ]
  },
  {
    "ContainingType": "WebApplication1.Controllers.TaskStatusController",
    "Method": "TaskStatusUpdate",
    "RelativePath": "api/TaskStatus/{id},{status}",
    "HttpMethod": "PUT",
    "IsController": true,
    "Order": 0,
    "Parameters": [
      {
        "Name": "taskid",
        "Type": "System.Int32",
        "IsRequired": false
      },
      {
        "Name": "status",
        "Type": "System.String",
        "IsRequired": true
      },
      {
        "Name": "id",
        "Type": "",
        "IsRequired": true
      }
    ],
    "ReturnTypes": [
      {
        "Type": "System.Collections.Generic.List\u00601[[WebApplication1.Models.TaskStatus, WebApplication1, Version=1.0.0.0, Culture=neutral, PublicKeyToken=null]]",
        "MediaTypes": [
          "text/plain",
          "application/json",
          "text/json"
        ],
        "StatusCode": 200
      }
    ]
  },
  {
    "ContainingType": "WebApplication1.Controllers.TaskTagController",
    "Method": "GetTaskTags",
    "RelativePath": "api/TaskTag/{taskId}",
    "HttpMethod": "GET",
    "IsController": true,
    "Order": 0,
    "Parameters": [
      {
        "Name": "taskId",
        "Type": "System.Int32",
        "IsRequired": true
      }
    ],
    "ReturnTypes": []
  },
  {
    "ContainingType": "WebApplication1.Controllers.TaskTagController",
    "Method": "RemoveTagFromTask",
    "RelativePath": "api/TaskTag/{taskId}/{tagId}",
    "HttpMethod": "DELETE",
    "IsController": true,
    "Order": 0,
    "Parameters": [
      {
        "Name": "taskId",
        "Type": "System.Int32",
        "IsRequired": true
      },
      {
        "Name": "tagId",
        "Type": "System.Int32",
        "IsRequired": true
      }
    ],
    "ReturnTypes": []
  },
  {
    "ContainingType": "WebApplication1.Controllers.TaskTagController",
    "Method": "AddTagToTask",
    "RelativePath": "api/TaskTag/{taskId}/{tagName}",
    "HttpMethod": "POST",
    "IsController": true,
    "Order": 0,
    "Parameters": [
      {
        "Name": "taskId",
        "Type": "System.Int32",
        "IsRequired": true
      },
      {
        "Name": "tagName",
        "Type": "System.String",
        "IsRequired": true
      }
    ],
    "ReturnTypes": []
  },
  {
    "ContainingType": "WebApplication1.Controllers.UsersController",
    "Method": "UsersGet",
    "RelativePath": "api/Users",
    "HttpMethod": "GET",
    "IsController": true,
    "Order": 0,
    "Parameters": [],
    "ReturnTypes": [
      {
        "Type": "System.Collections.Generic.List\u00601[[WebApplication1.Models.User, WebApplication1, Version=1.0.0.0, Culture=neutral, PublicKeyToken=null]]",
        "MediaTypes": [
          "text/plain",
          "application/json",
          "text/json"
        ],
        "StatusCode": 200
      }
    ]
  },
  {
    "ContainingType": "WebApplication1.Controllers.UsersController",
    "Method": "UserGet",
    "RelativePath": "api/Users/{id}",
    "HttpMethod": "GET",
    "IsController": true,
    "Order": 0,
    "Parameters": [
      {
        "Name": "id",
        "Type": "System.Int32",
        "IsRequired": true
      }
    ],
    "ReturnTypes": [
      {
        "Type": "WebApplication1.Models.User",
        "MediaTypes": [
          "text/plain",
          "application/json",
          "text/json"
        ],
        "StatusCode": 200
      }
    ]
  },
  {
    "ContainingType": "WebApplication1.Controllers.UsersController",
    "Method": "UsersDelete",
    "RelativePath": "api/Users/{id}",
    "HttpMethod": "DELETE",
    "IsController": true,
    "Order": 0,
    "Parameters": [
      {
        "Name": "id",
        "Type": "System.Int32",
        "IsRequired": true
      }
    ],
    "ReturnTypes": [
      {
        "Type": "System.Collections.Generic.List\u00601[[WebApplication1.Models.User, WebApplication1, Version=1.0.0.0, Culture=neutral, PublicKeyToken=null]]",
        "MediaTypes": [
          "text/plain",
          "application/json",
          "text/json"
        ],
        "StatusCode": 200
      }
    ]
  },
  {
    "ContainingType": "WebApplication1.Controllers.UsersController",
    "Method": "UserUpdate",
    "RelativePath": "api/Users/{id},{username}",
    "HttpMethod": "PUT",
    "IsController": true,
    "Order": 0,
    "Parameters": [
      {
        "Name": "id",
        "Type": "System.Int32",
        "IsRequired": true
      },
      {
        "Name": "username",
        "Type": "System.String",
        "IsRequired": true
      }
    ],
    "ReturnTypes": [
      {
        "Type": "System.Collections.Generic.List\u00601[[WebApplication1.Models.User, WebApplication1, Version=1.0.0.0, Culture=neutral, PublicKeyToken=null]]",
        "MediaTypes": [
          "text/plain",
          "application/json",
          "text/json"
        ],
        "StatusCode": 200
      }
    ]
  },
  {
    "ContainingType": "WebApplication1.Controllers.UsersController",
    "Method": "UsersSet",
    "RelativePath": "api/Users/{username}",
    "HttpMethod": "POST",
    "IsController": true,
    "Order": 0,
    "Parameters": [
      {
        "Name": "username",
        "Type": "System.String",
        "IsRequired": true
      }
    ],
    "ReturnTypes": [
      {
        "Type": "System.Collections.Generic.List\u00601[[WebApplication1.Models.User, WebApplication1, Version=1.0.0.0, Culture=neutral, PublicKeyToken=null]]",
        "MediaTypes": [
          "text/plain",
          "application/json",
          "text/json"
        ],
        "StatusCode": 200
      }
    ]
  }
]